{"completed_in":0.067,"max_id":261466357202300928,"max_id_str":"261466357202300928","page":1,"query":"from%3A%40BarackObama","refresh_url":"?since_id=261466357202300928&q=from%3A%40BarackObama&result_type=recent&include_entities=1","results":[{"created_at":"Thu, 25 Oct 2012 13:56:52 +0000","entities":{"hashtags":[],"urls":[],"user_mentions":[],"media":[{"id":261466357206495232,"id_str":"261466357206495232","indices":[18,38],"media_url":"http:\/\/p.twimg.com\/A6DqRD4CMAAdYn1.jpg","media_url_https":"https:\/\/p.twimg.com\/A6DqRD4CMAAdYn1.jpg","url":"http:\/\/t.co\/wCgd0lb8","display_url":"pic.twitter.com\/wCgd0lb8","expanded_url":"http:\/\/twitter.com\/BarackObama\/status\/261466357202300928\/photo\/1","type":"photo","sizes":{"orig":{"w":640,"h":640,"resize":"fit"},"medium":{"w":600,"h":600,"resize":"fit"},"large":{"w":640,"h":640,"resize":"fit"},"thumb":{"w":150,"h":150,"resize":"crop"},"small":{"w":340,"h":340,"resize":"fit"}}}]},"from_user":"BarackObama","from_user_id":813286,"from_user_id_str":"813286","from_user_name":"Barack Obama","geo":null,"id":261466357202300928,"id_str":"261466357202300928","iso_language_code":"en","metadata":{"result_type":"recent"},"profile_image_url":"http:\/\/a0.twimg.com\/profile_images\/2325704772\/wrrmef61i6jl91kwkmzq_normal.png","profile_image_url_https":"https:\/\/si0.twimg.com\/profile_images\/2325704772\/wrrmef61i6jl91kwkmzq_normal.png","source":"&lt;a href=&quot;http:\/\/twitter.com\/&quot;&gt;web&lt;\/a&gt;","text":"Babies for Obama: http:\/\/t.co\/wCgd0lb8","to_user":null,"to_user_id":0,"to_user_id_str":"0","to_user_name":null},{"created_at":"Thu, 25 Oct 2012 13:46:22 +0000","entities":{"hashtags":[],"urls":[],"user_mentions":[]},"from_user":"BarackObama","from_user_id":813286,"from_user_id_str":"813286","from_user_name":"Barack Obama","geo":null,"id":261463715206033408,"id_str":"261463715206033408","iso_language_code":"en","metadata":{"result_type":"recent"},"profile_image_url":"http:\/\/a0.twimg.com\/profile_images\/2325704772\/wrrmef61i6jl91kwkmzq_normal.png","profile_image_url_https":"https:\/\/si0.twimg.com\/profile_images\/2325704772\/wrrmef61i6jl91kwkmzq_normal.png","source":"&lt;a href=&quot;http:\/\/twitter.com\/&quot;&gt;web&lt;\/a&gt;","text":"Obama: \"Women should be making their own health care decisions. That\u2019s why the health care law we passed put those choices in your hands.\"","to_user":null,"to_user_id":0,"to_user_id_str":"0","to_user_name":null},{"created_at":"Thu, 25 Oct 2012 13:46:06 +0000","entities":{"hashtags":[],"urls":[{"url":"http:\/\/t.co\/mWL6H2Yy","expanded_url":"http:\/\/OFA.BO\/AULJUJ","display_url":"OFA.BO\/AULJUJ","indices":[119,139]}],"user_mentions":[]},"from_user":"BarackObama","from_user_id":813286,"from_user_id_str":"813286","from_user_name":"Barack Obama","geo":null,"id":261463649971994624,"id_str":"261463649971994624","iso_language_code":"en","metadata":{"result_type":"recent"},"profile_image_url":"http:\/\/a0.twimg.com\/profile_images\/2325704772\/wrrmef61i6jl91kwkmzq_normal.png","profile_image_url_https":"https:\/\/si0.twimg.com\/profile_images\/2325704772\/wrrmef61i6jl91kwkmzq_normal.png","source":"&lt;a href=&quot;http:\/\/twitter.com\/&quot;&gt;web&lt;\/a&gt;","text":"\"I don\u2019t think any politician in Washington, most of whom are male, should be making health care decisions for women.\" http:\/\/t.co\/mWL6H2Yy","to_user":null,"to_user_id":0,"to_user_id_str":"0","to_user_name":null},{"created_at":"Thu, 25 Oct 2012 13:34:06 +0000","entities":{"hashtags":[{"text":"AmericaForward","indices":[111,126]}],"urls":[],"user_mentions":[]},"from_user":"BarackObama","from_user_id":813286,"from_user_id_str":"813286","from_user_name":"Barack Obama","geo":null,"id":261460628617699328,"id_str":"261460628617699328","iso_language_code":"en","metadata":{"result_type":"recent"},"profile_image_url":"http:\/\/a0.twimg.com\/profile_images\/2325704772\/wrrmef61i6jl91kwkmzq_normal.png","profile_image_url_https":"https:\/\/si0.twimg.com\/profile_images\/2325704772\/wrrmef61i6jl91kwkmzq_normal.png","source":"&lt;a href=&quot;http:\/\/twitter.com\/&quot;&gt;web&lt;\/a&gt;","text":"President Obama: \u201cTrust matters, and Florida, you know me. You know I say what I mean, and I mean what I say.\u201d #AmericaForward","to_user":null,"to_user_id":0,"to_user_id_str":"0","to_user_name":null},{"created_at":"Thu, 25 Oct 2012 13:24:25 +0000","entities":{"hashtags":[],"urls":[],"user_mentions":[],"media":[{"id":261458191559299072,"id_str":"261458191559299072","indices":[62,82],"media_url":"http:\/\/p.twimg.com\/A6Di1weCEAAGN_8.png","media_url_https":"https:\/\/p.twimg.com\/A6Di1weCEAAGN_8.png","url":"http:\/\/t.co\/DJKyns2w","display_url":"pic.twitter.com\/DJKyns2w","expanded_url":"http:\/\/twitter.com\/BarackObama\/status\/261458191550910465\/photo\/1","type":"photo","sizes":{"small":{"w":340,"h":176,"resize":"fit"},"thumb":{"w":150,"h":150,"resize":"crop"},"medium":{"w":600,"h":310,"resize":"fit"},"orig":{"w":800,"h":413,"resize":"fit"},"large":{"w":800,"h":413,"resize":"fit"}}}]},"from_user":"BarackObama","from_user_id":813286,"from_user_id_str":"813286","from_user_name":"Barack Obama","geo":null,"id":261458191550910465,"id_str":"261458191550910465","iso_language_code":"en","metadata":{"result_type":"recent"},"profile_image_url":"http:\/\/a0.twimg.com\/profile_images\/2325704772\/wrrmef61i6jl91kwkmzq_normal.png","profile_image_url_https":"https:\/\/si0.twimg.com\/profile_images\/2325704772\/wrrmef61i6jl91kwkmzq_normal.png","source":"&lt;a href=&quot;http:\/\/twitter.com\/&quot;&gt;web&lt;\/a&gt;","text":"The sun's fully up as the President takes the stage in Tampa. http:\/\/t.co\/DJKyns2w","to_user":null,"to_user_id":0,"to_user_id_str":"0","to_user_name":null},{"created_at":"Thu, 25 Oct 2012 13:13:59 +0000","entities":{"hashtags":[],"urls":[{"url":"http:\/\/t.co\/k9AT95B3","expanded_url":"http:\/\/OFA.BO\/AkA2no","display_url":"OFA.BO\/AkA2no","indices":[85,105]}],"user_mentions":[]},"from_user":"BarackObama","from_user_id":813286,"from_user_id_str":"813286","from_user_name":"Barack Obama","geo":null,"id":261455568538046464,"id_str":"261455568538046464","iso_language_code":"en","metadata":{"result_type":"recent"},"profile_image_url":"http:\/\/a0.twimg.com\/profile_images\/2325704772\/wrrmef61i6jl91kwkmzq_normal.png","profile_image_url_https":"https:\/\/si0.twimg.com\/profile_images\/2325704772\/wrrmef61i6jl91kwkmzq_normal.png","source":"&lt;a href=&quot;http:\/\/twitter.com\/&quot;&gt;web&lt;\/a&gt;","text":"A bit of morning shootaround at the firehouse before the day's first event in Tampa: http:\/\/t.co\/k9AT95B3","to_user":null,"to_user_id":0,"to_user_id_str":"0","to_user_name":null},{"created_at":"Thu, 25 Oct 2012 13:09:34 +0000","entities":{"hashtags":[],"urls":[{"url":"http:\/\/t.co\/6WtGhwjZ","expanded_url":"http:\/\/OFA.BO\/kDmfPo","display_url":"OFA.BO\/kDmfPo","indices":[40,60]}],"user_mentions":[]},"from_user":"BarackObama","from_user_id":813286,"from_user_id_str":"813286","from_user_name":"Barack Obama","geo":null,"id":261454457513058305,"id_str":"261454457513058305","iso_language_code":"en","metadata":{"result_type":"recent"},"profile_image_url":"http:\/\/a0.twimg.com\/profile_images\/2325704772\/wrrmef61i6jl91kwkmzq_normal.png","profile_image_url_https":"https:\/\/si0.twimg.com\/profile_images\/2325704772\/wrrmef61i6jl91kwkmzq_normal.png","source":"&lt;a href=&quot;http:\/\/twitter.com\/&quot;&gt;web&lt;\/a&gt;","text":"\"Thank you for everything you guys do.\" http:\/\/t.co\/6WtGhwjZ","to_user":null,"to_user_id":0,"to_user_id_str":"0","to_user_name":null}],"results_per_page":100,"since_id":261450037727461376,"since_id_str":"261450037727461376"}
